geonode_ows_endpoints/__init__.py
geonode_ows_endpoints/custom_urls.py
geonode_ows_endpoints/models.py
geonode_ows_endpoints/tests.py
geonode_ows_endpoints/urls.py
geonode_ows_endpoints/views.py
geonode_ows_endpoints-0.2.dist-info/DESCRIPTION.rst
geonode_ows_endpoints-0.2.dist-info/METADATA
geonode_ows_endpoints-0.2.dist-info/RECORD
geonode_ows_endpoints-0.2.dist-info/WHEEL
geonode_ows_endpoints-0.2.dist-info/metadata.json
geonode_ows_endpoints-0.2.dist-info/top_level.txt
