Metadata-Version: 2.0
Name: geonode-ows-endpoints
Version: 0.2
Summary: GeoNode OWS listing. Exposes url which lists all OWS endpoints used by layers.
Home-page: https://github.com/geosolutions-it/geonode-ows-endpoints
Author: Cezary Statkiewicz
Author-email: cezary.statkiewicz@geo-solutions.it
License: UNKNOWN
Keywords: geonode,monitoring,geohealthcheck,integration api,gis
Platform: UNKNOWN
Classifier: Development Status :: 4 - Beta
Classifier: Environment :: Web Environment
Classifier: Environment :: Plugins
Classifier: Framework :: Django
Classifier: Intended Audience :: System Administrators
Classifier: License :: OSI Approved :: GNU General Public License v3 or later (GPLv3+)
Classifier: Operating System :: OS Independent
Classifier: Programming Language :: Python
Classifier: Topic :: Internet :: WWW/HTTP :: Dynamic Content
Classifier: Topic :: Scientific/Engineering :: GIS
Requires-Dist: GeoNode (<2.7)
